[
    {
      "id": 1,
      "name": "Alice Smith",
      "title": "Update project report",
      "description": "Add Q3 financials to the report",
      "status": "pending"
    },
    {
      "id": 2,
      "name": "Bob Johnson",
      "title": "Code review",
      "description": "Review PR for the new login feature",
      "status": "approval"
    },
    {
      "id": 3,
      "name": "Charlie Brown",
      "title": "Client feedback",
      "description": "Incorporate client feedback into the design",
      "status": "pending"
    },
    {
      "id": 4,
      "name": "Diana Prince",
      "title": "Research topic",
      "description": "Compile information for the new marketing campaign",
      "status": "in-progress"
    },
    {
      "id": 5,
      "name": "Evan Wright",
      "title": "Write documentation",
      "description": "Document API usage for new features",
      "status": "approval"
    },
    {
      "id": 6,
      "name": "Fiona Green",
      "title": "Organize workshop",
      "description": "Plan the workshop schedule and resources",
      "status": "in-progress"
    },
    {
      "id": 7,
      "name": "George Taylor",
      "title": "Test module",
      "description": "Perform unit testing on the inventory module",
      "status": "pending"
    },
    {
      "id": 8,
      "name": "Hannah Adams",
      "title": "Social media plan",
      "description": "Draft a social media content strategy",
      "status": "approval"
    },
    {
      "id": 9,
      "name": "Ian Roberts",
      "title": "Setup environment",
      "description": "Configure the development environment for the team",
      "status": "in-progress"
    },
    {
      "id": 10,
      "name": "Jenna Lee",
      "title": "Audit compliance",
      "description": "Ensure the project meets compliance standards",
      "status": "approval"
    },
    {
      "id": 11,
      "name": "Kevin Carter",
      "title": "Database backup",
      "description": "Schedule and verify database backups",
      "status": "pending"
    },
    {
      "id": 12,
      "name": "Liam Mitchell",
      "title": "Deploy update",
      "description": "Deploy the latest update to the staging server",
      "status": "in-progress"
    }
  ]
  